TgMelon/__init__.py
TgMelon/test.py
TgMelon-0.0.0.dist-info/METADATA
TgMelon-0.0.0.dist-info/WHEEL
TgMelon-0.0.0.dist-info/top_level.txt
TgMelon-0.0.0.dist-info/RECORD
