Metadata-Version: 2.1
Name: TgMelon
Version: 0.0.0
Summary: An advanced and comprehensive library for managing Telegram bots
Author: Ahmed Negm
Author-email: a7mednegm.x@gmail.com
Classifier: Programming Language :: Python :: 3
Classifier: License :: OSI Approved :: MIT License
Classifier: Operating System :: OS Independent
Requires-Dist: flask
Requires-Dist: urllib3
